stopwatch/__init__.py
stopwatch/stopwatch.py
stopwatch.py-2.0.0.dist-info/LICENSE
stopwatch.py-2.0.0.dist-info/METADATA
stopwatch.py-2.0.0.dist-info/WHEEL
stopwatch.py-2.0.0.dist-info/top_level.txt
stopwatch.py-2.0.0.dist-info/RECORD
